Abhay_STT/__init__.py
AbhaySpeechToText-0.2.dist-info/METADATA
AbhaySpeechToText-0.2.dist-info/WHEEL
AbhaySpeechToText-0.2.dist-info/top_level.txt
AbhaySpeechToText-0.2.dist-info/RECORD
